nonebot_plugin_picmenu_next/__init__.py
nonebot_plugin_picmenu_next/__main__.py
nonebot_plugin_picmenu_next/config.py
nonebot_plugin_picmenu_next/ft_parser.py
nonebot_plugin_picmenu_next/utils.py
nonebot_plugin_picmenu_next/data_source/__init__.py
nonebot_plugin_picmenu_next/data_source/collect.py
nonebot_plugin_picmenu_next/data_source/mixin.py
nonebot_plugin_picmenu_next/data_source/models.py
nonebot_plugin_picmenu_next/data_source/pinyin.py
nonebot_plugin_picmenu_next/res/gan_shen_me.jpg
nonebot_plugin_picmenu_next/templates/__init__.py
nonebot_plugin_picmenu_next/templates/pw_utils.py
nonebot_plugin_picmenu_next/templates/default/__init__.py
nonebot_plugin_picmenu_next/templates/default/res/base.html.jinja
nonebot_plugin_picmenu_next/templates/default/res/detail.html.jinja
nonebot_plugin_picmenu_next/templates/default/res/index.html.jinja
nonebot_plugin_picmenu_next/templates/default/res/css/base.css
nonebot_plugin_picmenu_next/templates/default/res/css/dark.css
nonebot_plugin_picmenu_next/templates/default/res/css/detail.css
nonebot_plugin_picmenu_next/templates/default/res/css/index.css
nonebot_plugin_picmenu_next/templates/default/res/js/base.js
nonebot_plugin_picmenu_next/templates/default/res/js/tsconfig.json
nonebot_plugin_picmenu_next/templates/default/res/third-party/code-colorful.css
nonebot_plugin_picmenu_next/templates/default/res/third-party/code-github-dark.css
nonebot_plugin_picmenu_next/templates/default/res/third-party/katex.min.css
nonebot_plugin_picmenu_next/templates/default/res/third-party/katex.min.js
nonebot_plugin_picmenu_next/templates/default/res/third-party/fonts/KaTeX_AMS-Regular.ttf
nonebot_plugin_picmenu_next/templates/default/res/third-party/fonts/KaTeX_AMS-Regular.woff
nonebot_plugin_picmenu_next/templates/default/res/third-party/fonts/KaTeX_AMS-Regular.woff2
nonebot_plugin_picmenu_next/templates/default/res/third-party/fonts/KaTeX_Caligraphic-Bold.ttf
nonebot_plugin_picmenu_next-0.1.6.post1.dist-info/METADATA
nonebot_plugin_picmenu_next-0.1.6.post1.dist-info/WHEEL
nonebot_plugin_picmenu_next-0.1.6.post1.dist-info/licenses/LICENSE
nonebot_plugin_picmenu_next-0.1.6.post1.dist-info/RECORD
