Metadata-Version: 2.4
Name: nonebot-plugin-picmenu-next
Version: 0.1.6.post1
Summary: Template plugin project
Project-URL: homepage, https://github.com/lgc-NB2Dev/nonebot-plugin-picmenu-next
Author-email: LgCookie <lgc2333@126.com>
License: MIT
License-File: LICENSE
Requires-Python: <4.0,>=3.10
Requires-Dist: cookit[jinja,loguru,nonebot-alconna,nonebot-localstore,pw,pyd]>=0.13.0
Requires-Dist: jieba>=0.42.1
Requires-Dist: markdown-it-py[plugins]>=4.0.0
Requires-Dist: nonebot-plugin-alconna>=0.59.4
Requires-Dist: nonebot-plugin-htmlrender>=0.6.6
Requires-Dist: nonebot-plugin-localstore>=0.7.4
Requires-Dist: nonebot2>=2.4.3
Requires-Dist: pygments>=2.19.2
Requires-Dist: pypinyin>=0.55.0
Requires-Dist: thefuzz>=0.22.1
Provides-Extra: all
Requires-Dist: ruamel-yaml>=0.18.14; extra == 'all'
Requires-Dist: tomli>=2.0.1; (python_version < '3.11') and extra == 'all'
Provides-Extra: toml
Requires-Dist: tomli>=2.0.1; (python_version < '3.11') and extra == 'toml'
Provides-Extra: yaml
Requires-Dist: ruamel-yaml>=0.18.14; extra == 'yaml'
